LICENSE
MANIFEST.in
README.rst
requirements.txt
requirements_dev.txt
setup.cfg
setup.py
docs/Makefile
docs/conf.py
docs/getting-started.rst
docs/index.rst
docs/make.bat
docs/source/example.rst
docs/source/stream_tap.rst
docs/source/stream_tap.tests.rst
stream_tap/__init__.py
stream_tap/_meta.py
stream_tap.egg-info/PKG-INFO
stream_tap.egg-info/SOURCES.txt
stream_tap.egg-info/dependency_links.txt
stream_tap.egg-info/top_level.txt
stream_tap/tests/__init__.py
stream_tap/tests/test_tap.py
stream_tap/tests/test_version.py