Metadata-Version: 1.1
Name: stream_tap
Version: 0.9.1
Summary: Capture data from an iterator as it gets pulled down stream.
Home-page: https://github.com/johnwlockwood/stream_tap
Author: John W Lockwood IV
Author-email: john@tackletronics.com
License:                                  Apache License
